odoo8_addon_account_cutoff_accrual_picking-8.0.0.1.0.99.dev9-py3.8-nspkg.pth
odoo_addons/account_cutoff_accrual_picking/README.rst
odoo_addons/account_cutoff_accrual_picking/__init__.py
odoo_addons/account_cutoff_accrual_picking/__openerp__.py
odoo_addons/account_cutoff_accrual_picking/i18n/account_cutoff_accrual_picking.pot
odoo_addons/account_cutoff_accrual_picking/i18n/ar.po
odoo_addons/account_cutoff_accrual_picking/i18n/bg.po
odoo_addons/account_cutoff_accrual_picking/i18n/bs.po
odoo_addons/account_cutoff_accrual_picking/i18n/ca.po
odoo_addons/account_cutoff_accrual_picking/i18n/cs.po
odoo_addons/account_cutoff_accrual_picking/i18n/da.po
odoo_addons/account_cutoff_accrual_picking/i18n/de.po
odoo_addons/account_cutoff_accrual_picking/i18n/el_GR.po
odoo_addons/account_cutoff_accrual_picking/i18n/en_GB.po
odoo_addons/account_cutoff_accrual_picking/i18n/es.po
odoo_addons/account_cutoff_accrual_picking/i18n/es_AR.po
odoo_addons/account_cutoff_accrual_picking/i18n/es_BO.po
odoo_addons/account_cutoff_accrual_picking/i18n/es_CL.po
odoo_addons/account_cutoff_accrual_picking/i18n/es_CO.po
odoo_addons/account_cutoff_accrual_picking/i18n/es_CR.po
odoo_addons/account_cutoff_accrual_picking/i18n/es_DO.po
odoo_addons/account_cutoff_accrual_picking/i18n/es_EC.po
odoo_addons/account_cutoff_accrual_picking/i18n/es_MX.po
odoo_addons/account_cutoff_accrual_picking/i18n/es_PY.po
odoo_addons/account_cutoff_accrual_picking/i18n/es_VE.po
odoo_addons/account_cutoff_accrual_picking/i18n/et.po
odoo_addons/account_cutoff_accrual_picking/i18n/eu.po
odoo_addons/account_cutoff_accrual_picking/i18n/fa.po
odoo_addons/account_cutoff_accrual_picking/i18n/fi.po
odoo_addons/account_cutoff_accrual_picking/i18n/fr.po
odoo_addons/account_cutoff_accrual_picking/i18n/gl.po
odoo_addons/account_cutoff_accrual_picking/i18n/he.po
odoo_addons/account_cutoff_accrual_picking/i18n/hr.po
odoo_addons/account_cutoff_accrual_picking/i18n/hu.po
odoo_addons/account_cutoff_accrual_picking/i18n/id.po
odoo8_addon_account_cutoff_accrual_picking-8.0.0.1.0.99.dev9.dist-info/METADATA
odoo8_addon_account_cutoff_accrual_picking-8.0.0.1.0.99.dev9.dist-info/WHEEL
odoo8_addon_account_cutoff_accrual_picking-8.0.0.1.0.99.dev9.dist-info/namespace_packages.txt
odoo8_addon_account_cutoff_accrual_picking-8.0.0.1.0.99.dev9.dist-info/top_level.txt
odoo8_addon_account_cutoff_accrual_picking-8.0.0.1.0.99.dev9.dist-info/RECORD
